PyBiPlot/__init__.py
PyBiPlot/pybiplot.py
pybiplot-0.0.7.dist-info/LICENSE
pybiplot-0.0.7.dist-info/METADATA
pybiplot-0.0.7.dist-info/WHEEL
pybiplot-0.0.7.dist-info/top_level.txt
pybiplot-0.0.7.dist-info/RECORD
