Metadata-Version: 2.1
Name: pybiplot
Version: 0.0.7
Summary: R's BiPlot visual for PCA in Python
Home-page: https://github.com/adames-ouro/pybiplot
Author: Carlos A. Adames Ramos
Author-email: carlos.adames.ramos@gmail.com
Classifier: Programming Language :: Python :: 3
Classifier: License :: OSI Approved :: MIT License
Classifier: Operating System :: OS Independent
Requires-Python: >=3.6
License-File: LICENSE
Requires-Dist: pandas >=2.2.2
Requires-Dist: matplotlib >=3.9.0
